ellipticbn/__init__.py
ellipticbn/__version__.py
ellipticbn/core.py
ellipticbn/run_all.py
ellipticbn/data/atom-colors.csv
ellipticbn/data/palette-colors.txt
ellipticbn-2.1.2.dist-info/LICENSE
ellipticbn-2.1.2.dist-info/METADATA
ellipticbn-2.1.2.dist-info/WHEEL
ellipticbn-2.1.2.dist-info/entry_points.txt
ellipticbn-2.1.2.dist-info/top_level.txt
ellipticbn-2.1.2.dist-info/RECORD
