Metadata-Version: 2.1
Name: ellipticbn
Version: 2.1.2
Summary: Automatically measure the ellipticity of cucurbituril macrocycles!
Author-email: Michael Shavlik <mshavlik@uoregon.edu>, Mike Harms <harms@uoregon.edu>
Maintainer-email: Mike Harms <harms@uoregon.edu>
License: MIT License
Project-URL: Repository, https://github.com/harmslab/ellipticbn.git
Project-URL: Bug Tracker, https://github.com/harmslab/ellipticbn/issues
Keywords: macrocycle,cucurbituril,ellipticity,chemistry,geometry,host,guest
Classifier: Development Status :: 5 - Production/Stable
Classifier: Programming Language :: Python
Requires-Python: >=3.9
License-File: LICENSE
Requires-Dist: numpy >=1.10
Requires-Dist: networkx
Requires-Dist: scikit-learn
Requires-Dist: plotly
Requires-Dist: pandas
Requires-Dist: matplotlib
Requires-Dist: xlsxwriter
Requires-Dist: mdanalysis
Requires-Dist: scipy
Provides-Extra: test
Requires-Dist: coverage ; extra == 'test'
Requires-Dist: flake8 ; extra == 'test'
Requires-Dist: pytest ; extra == 'test'
